DESCRIPTION.rst
MANIFEST.in
README.rst
setup.cfg
setup.py
bin/vai
vai/BugReport.py
vai/Debug.py
vai/EditArea.py
vai/EditAreaEventFilter.py
vai/Editor.py
vai/EditorApp.py
vai/InfoHoverBox.py
vai/Search.py
vai/SymbolLookupDb.py
vai/__init__.py
vai/paths.py
vai.egg-info/PKG-INFO
vai.egg-info/SOURCES.txt
vai.egg-info/dependency_links.txt
vai.egg-info/entry_points.txt
vai.egg-info/not-zip-safe
vai.egg-info/requires.txt
vai.egg-info/top_level.txt
vai/controllers/CommandBarController.py
vai/controllers/EditAreaController.py
vai/controllers/EditorController.py
vai/controllers/SideRulerController.py
vai/controllers/StatusBarController.py
vai/controllers/__init__.py
vai/lexer/Lexer.py
vai/lexer/__init__.py
vai/lexer/token.py
vai/linting/LinterResult.py
vai/linting/PyFlakesLinter.py
vai/linting/PyLintLinter.py
vai/linting/__init__.py
vai/models/Buffer.py
vai/models/BufferList.py
vai/models/CommandHistory.py
vai/models/Configuration.py
vai/models/DocumentMetaInfo.py
vai/models/EditAreaModel.py
vai/models/EditorMode.py
vai/models/EditorState.py
vai/models/GlobalState.py
vai/models/Icons.py
vai/models/LineMetaInfo.py
vai/models/Selection.py
vai/models/SyntaxColors.py
vai/models/TextDocument.py
vai/models/TextDocumentCursor.py
vai/models/__init__.py
vai/models/commands/BreakLineCommand.py
vai/models/commands/BufferCommand.py
vai/models/commands/CommandResult.py
vai/models/commands/DedentCommand.py
vai/models/commands/DeleteLineAtCursorCommand.py
vai/models/commands/DeleteLinesCommand.py
vai/models/commands/DeleteSingleCharAfterCommand.py
vai/models/commands/DeleteSingleCharCommand.py
vai/models/commands/DeleteToEndOfLineCommand.py
vai/models/commands/DeleteToEndOfWordCommand.py
vai/models/commands/IndentCommand.py
vai/models/commands/InsertFileCommand.py
vai/models/commands/InsertLineAfterCommand.py
vai/models/commands/InsertLineCommand.py
vai/models/commands/InsertMultiLineCommand.py
vai/models/commands/InsertStringCommand.py
vai/models/commands/JoinWithNextLineCommand.py
vai/models/commands/NewLineAfterCommand.py
vai/models/commands/NewLineCommand.py
vai/models/commands/ReplaceSingleCharCommand.py
vai/models/commands/__init__.py
vai/plugins/__init__.py
