Metadata-Version: 1.1
Name: vai
Version: 1.7
Summary: VAI is a console-based IDE similar to VIM
Home-page: https://github.com/stefanoborini/vai
Author: Stefano Borini
Author-email: stefano.borini@gmail.com
License: BSD
Keywords: editor
Platform: UNKNOWN
Classifier: Development Status :: 3 - Alpha
Classifier: Topic :: Text Editors
Classifier: License :: OSI Approved :: BSD License
Classifier: Intended Audience :: Developers
Classifier: Programming Language :: Python :: 3.4
